ppcdis/__init__.py
ppcdis/analyser.py
ppcdis/assets.py
ppcdis/binarybase.py
ppcdis/binarydiff.py
ppcdis/binarydol.py
ppcdis/binarylect.py
ppcdis/binaryrel.py
ppcdis/binaryyml.py
ppcdis/csutil.py
ppcdis/disassembler.py
ppcdis/elf2dol.py
ppcdis/elf2rel.py
ppcdis/fastelf.py
ppcdis/fileutil.py
ppcdis/instrcats.py
ppcdis/labelinfo_pb2.py
ppcdis/lcf.py
ppcdis/orderdata.py
ppcdis/overrides.py
ppcdis/relextern.py
ppcdis/relocinfo_pb2.py
ppcdis/relocs.py
ppcdis/slices.py
ppcdis/symbols.py
ppcdis/version.py
ppcdis_protobuf-0.0.2.data/scripts/analyser.py
ppcdis_protobuf-0.0.2.data/scripts/disassembler.py
ppcdis_protobuf-0.0.2.dist-info/LICENSE.md
ppcdis_protobuf-0.0.2.dist-info/METADATA
ppcdis_protobuf-0.0.2.dist-info/WHEEL
ppcdis_protobuf-0.0.2.dist-info/top_level.txt
ppcdis_protobuf-0.0.2.dist-info/RECORD
